{"info":{"file":"wwwroot\\app\\bootstrap.js","fileShort":"wwwroot\\app\\bootstrap.js","fileSafe":"wwwroot_app_bootstrap_js","link":"files/wwwroot_app_bootstrap_js/index.html"},"complexity":{"aggregate":{"sloc":{"logical":32,"physical":59},"cyclomatic":3,"halstead":{"operators":{"distinct":12,"total":84,"identifiers":["__stripped__"]},"operands":{"distinct":55,"total":139,"identifiers":["__stripped__"]},"length":223,"vocabulary":67,"difficulty":15.163636363636364,"volume":1352.7378894720832,"effort":20512.42545126759,"bugs":0.45091262982402774,"time":1139.5791917370884},"params":12,"line":1,"cyclomaticDensity":9.375,"complexity":{"cyclomatic":3,"sloc":{"logical":32,"physical":59},"halstead":{"operators":{"distinct":12,"total":84,"identifiers":["__stripped__"]},"operands":{"distinct":55,"total":139,"identifiers":["__stripped__"]},"length":223,"vocabulary":67,"difficulty":15.163636363636364,"volume":1352.7378894720832,"effort":20512.42545126759,"bugs":0.45091262982402774,"time":1139.5791917370884}}},"functions":[{"name":"<anonymous>","sloc":{"logical":13,"physical":59},"cyclomatic":1,"halstead":{"operators":{"distinct":9,"total":20,"identifiers":["__stripped__"]},"operands":{"distinct":16,"total":29,"identifiers":["__stripped__"]},"length":49,"vocabulary":25,"difficulty":8.15625,"volume":227.5489532989615,"effort":1855.9461503446546,"bugs":0.07584965109965383,"time":103.10811946359192},"params":2,"line":1,"cyclomaticDensity":7.6923076923076925,"complexity":{"cyclomatic":1,"sloc":{"logical":13,"physical":59},"halstead":{"operators":{"distinct":9,"total":20,"identifiers":["__stripped__"]},"operands":{"distinct":16,"total":29,"identifiers":["__stripped__"]},"length":49,"vocabulary":25,"difficulty":8.15625,"volume":227.5489532989615,"effort":1855.9461503446546,"bugs":0.07584965109965383,"time":103.10811946359192}}},{"name":"<anonymous>","sloc":{"logical":0,"physical":1},"cyclomatic":1,"halstead":{"operators":{"distinct":0,"total":0,"identifiers":["__stripped__"]},"operands":{"distinct":1,"total":1,"identifiers":["__stripped__"]},"length":1,"vocabulary":1,"difficulty":0,"volume":0,"effort":0,"bugs":0,"time":0},"params":1,"line":7,"cyclomaticDensity":null,"complexity":{"cyclomatic":1,"sloc":{"logical":0,"physical":1},"halstead":{"operators":{"distinct":0,"total":0,"identifiers":["__stripped__"]},"operands":{"distinct":1,"total":1,"identifiers":["__stripped__"]},"length":1,"vocabulary":1,"difficulty":0,"volume":0,"effort":0,"bugs":0,"time":0}}},{"name":"<anonymous>","sloc":{"logical":1,"physical":3},"cyclomatic":1,"halstead":{"operators":{"distinct":1,"total":1,"identifiers":["__stripped__"]},"operands":{"distinct":2,"total":3,"identifiers":["__stripped__"]},"length":4,"vocabulary":3,"difficulty":0.75,"volume":6.339850002884625,"effort":4.754887502163469,"bugs":0.002113283334294875,"time":0.2641604167868594},"params":1,"line":8,"cyclomaticDensity":100,"complexity":{"cyclomatic":1,"sloc":{"logical":1,"physical":3},"halstead":{"operators":{"distinct":1,"total":1,"identifiers":["__stripped__"]},"operands":{"distinct":2,"total":3,"identifiers":["__stripped__"]},"length":4,"vocabulary":3,"difficulty":0.75,"volume":6.339850002884625,"effort":4.754887502163469,"bugs":0.002113283334294875,"time":0.2641604167868594}}},{"name":"<anonymous>","sloc":{"logical":1,"physical":3},"cyclomatic":1,"halstead":{"operators":{"distinct":1,"total":1,"identifiers":["__stripped__"]},"operands":{"distinct":2,"total":3,"identifiers":["__stripped__"]},"length":4,"vocabulary":3,"difficulty":0.75,"volume":6.339850002884625,"effort":4.754887502163469,"bugs":0.002113283334294875,"time":0.2641604167868594},"params":1,"line":11,"cyclomaticDensity":100,"complexity":{"cyclomatic":1,"sloc":{"logical":1,"physical":3},"halstead":{"operators":{"distinct":1,"total":1,"identifiers":["__stripped__"]},"operands":{"distinct":2,"total":3,"identifiers":["__stripped__"]},"length":4,"vocabulary":3,"difficulty":0.75,"volume":6.339850002884625,"effort":4.754887502163469,"bugs":0.002113283334294875,"time":0.2641604167868594}}},{"name":"<anonymous>","sloc":{"logical":1,"physical":3},"cyclomatic":1,"halstead":{"operators":{"distinct":1,"total":1,"identifiers":["__stripped__"]},"operands":{"distinct":2,"total":3,"identifiers":["__stripped__"]},"length":4,"vocabulary":3,"difficulty":0.75,"volume":6.339850002884625,"effort":4.754887502163469,"bugs":0.002113283334294875,"time":0.2641604167868594},"params":1,"line":14,"cyclomaticDensity":100,"complexity":{"cyclomatic":1,"sloc":{"logical":1,"physical":3},"halstead":{"operators":{"distinct":1,"total":1,"identifiers":["__stripped__"]},"operands":{"distinct":2,"total":3,"identifiers":["__stripped__"]},"length":4,"vocabulary":3,"difficulty":0.75,"volume":6.339850002884625,"effort":4.754887502163469,"bugs":0.002113283334294875,"time":0.2641604167868594}}},{"name":"<anonymous>","sloc":{"logical":1,"physical":3},"cyclomatic":1,"halstead":{"operators":{"distinct":1,"total":1,"identifiers":["__stripped__"]},"operands":{"distinct":2,"total":3,"identifiers":["__stripped__"]},"length":4,"vocabulary":3,"difficulty":0.75,"volume":6.339850002884625,"effort":4.754887502163469,"bugs":0.002113283334294875,"time":0.2641604167868594},"params":1,"line":17,"cyclomaticDensity":100,"complexity":{"cyclomatic":1,"sloc":{"logical":1,"physical":3},"halstead":{"operators":{"distinct":1,"total":1,"identifiers":["__stripped__"]},"operands":{"distinct":2,"total":3,"identifiers":["__stripped__"]},"length":4,"vocabulary":3,"difficulty":0.75,"volume":6.339850002884625,"effort":4.754887502163469,"bugs":0.002113283334294875,"time":0.2641604167868594}}},{"name":"<anonymous>","sloc":{"logical":1,"physical":3},"cyclomatic":1,"halstead":{"operators":{"distinct":1,"total":1,"identifiers":["__stripped__"]},"operands":{"distinct":2,"total":3,"identifiers":["__stripped__"]},"length":4,"vocabulary":3,"difficulty":0.75,"volume":6.339850002884625,"effort":4.754887502163469,"bugs":0.002113283334294875,"time":0.2641604167868594},"params":1,"line":20,"cyclomaticDensity":100,"complexity":{"cyclomatic":1,"sloc":{"logical":1,"physical":3},"halstead":{"operators":{"distinct":1,"total":1,"identifiers":["__stripped__"]},"operands":{"distinct":2,"total":3,"identifiers":["__stripped__"]},"length":4,"vocabulary":3,"difficulty":0.75,"volume":6.339850002884625,"effort":4.754887502163469,"bugs":0.002113283334294875,"time":0.2641604167868594}}},{"name":"<anonymous>","sloc":{"logical":1,"physical":3},"cyclomatic":1,"halstead":{"operators":{"distinct":1,"total":1,"identifiers":["__stripped__"]},"operands":{"distinct":2,"total":3,"identifiers":["__stripped__"]},"length":4,"vocabulary":3,"difficulty":0.75,"volume":6.339850002884625,"effort":4.754887502163469,"bugs":0.002113283334294875,"time":0.2641604167868594},"params":1,"line":23,"cyclomaticDensity":100,"complexity":{"cyclomatic":1,"sloc":{"logical":1,"physical":3},"halstead":{"operators":{"distinct":1,"total":1,"identifiers":["__stripped__"]},"operands":{"distinct":2,"total":3,"identifiers":["__stripped__"]},"length":4,"vocabulary":3,"difficulty":0.75,"volume":6.339850002884625,"effort":4.754887502163469,"bugs":0.002113283334294875,"time":0.2641604167868594}}},{"name":"<anonymous>","sloc":{"logical":1,"physical":3},"cyclomatic":1,"halstead":{"operators":{"distinct":1,"total":1,"identifiers":["__stripped__"]},"operands":{"distinct":2,"total":3,"identifiers":["__stripped__"]},"length":4,"vocabulary":3,"difficulty":0.75,"volume":6.339850002884625,"effort":4.754887502163469,"bugs":0.002113283334294875,"time":0.2641604167868594},"params":1,"line":26,"cyclomaticDensity":100,"complexity":{"cyclomatic":1,"sloc":{"logical":1,"physical":3},"halstead":{"operators":{"distinct":1,"total":1,"identifiers":["__stripped__"]},"operands":{"distinct":2,"total":3,"identifiers":["__stripped__"]},"length":4,"vocabulary":3,"difficulty":0.75,"volume":6.339850002884625,"effort":4.754887502163469,"bugs":0.002113283334294875,"time":0.2641604167868594}}},{"name":"<anonymous>","sloc":{"logical":1,"physical":3},"cyclomatic":1,"halstead":{"operators":{"distinct":1,"total":1,"identifiers":["__stripped__"]},"operands":{"distinct":2,"total":3,"identifiers":["__stripped__"]},"length":4,"vocabulary":3,"difficulty":0.75,"volume":6.339850002884625,"effort":4.754887502163469,"bugs":0.002113283334294875,"time":0.2641604167868594},"params":1,"line":29,"cyclomaticDensity":100,"complexity":{"cyclomatic":1,"sloc":{"logical":1,"physical":3},"halstead":{"operators":{"distinct":1,"total":1,"identifiers":["__stripped__"]},"operands":{"distinct":2,"total":3,"identifiers":["__stripped__"]},"length":4,"vocabulary":3,"difficulty":0.75,"volume":6.339850002884625,"effort":4.754887502163469,"bugs":0.002113283334294875,"time":0.2641604167868594}}},{"name":"execute","sloc":{"logical":7,"physical":26},"cyclomatic":3,"halstead":{"operators":{"distinct":9,"total":31,"identifiers":["__stripped__"]},"operands":{"distinct":27,"total":40,"identifiers":["__stripped__"]},"length":71,"vocabulary":36,"difficulty":6.666666666666666,"volume":367.0646751024042,"effort":2447.0978340160277,"bugs":0.1223548917008014,"time":135.9498796675571},"params":0,"line":32,"cyclomaticDensity":42.857142857142854,"complexity":{"cyclomatic":3,"sloc":{"logical":7,"physical":26},"halstead":{"operators":{"distinct":9,"total":31,"identifiers":["__stripped__"]},"operands":{"distinct":27,"total":40,"identifiers":["__stripped__"]},"length":71,"vocabulary":36,"difficulty":6.666666666666666,"volume":367.0646751024042,"effort":2447.0978340160277,"bugs":0.1223548917008014,"time":135.9498796675571}}},{"name":"Office.initialize","sloc":{"logical":3,"physical":11},"cyclomatic":1,"halstead":{"operators":{"distinct":5,"total":21,"identifiers":["__stripped__"]},"operands":{"distinct":23,"total":32,"identifiers":["__stripped__"]},"length":53,"vocabulary":28,"difficulty":3.4782608695652173,"volume":254.78981086905299,"effort":886.2254291097495,"bugs":0.084929936956351,"time":49.23474606165275},"params":1,"line":34,"cyclomaticDensity":33.33333333333333,"complexity":{"cyclomatic":1,"sloc":{"logical":3,"physical":11},"halstead":{"operators":{"distinct":5,"total":21,"identifiers":["__stripped__"]},"operands":{"distinct":23,"total":32,"identifiers":["__stripped__"]},"length":53,"vocabulary":28,"difficulty":3.4782608695652173,"volume":254.78981086905299,"effort":886.2254291097495,"bugs":0.084929936956351,"time":49.23474606165275}}}],"dependencies":[],"maintainability":78.83448651681002,"loc":2.5833333333333335,"cyclomatic":1.1666666666666667,"effort":435.60904279064493,"params":1,"module":"wwwroot\\app\\bootstrap.js"},"jshint":{"messages":[{"severity":"error","line":58,"column":6,"message":"Missing semicolon.","source":"Missing semicolon."}]}}